{
  "lastUpdated": "2026-05-20T22:47:55.878Z",
  "indices": {
    "^GSPC": {
      "price": "7,432.97",
      "changeText": "▲ 0.4%",
      "changePercent": "+0.40",
      "status": "up"
    },
    "^IXIC": {
      "price": "26,270.36",
      "changeText": "▲ 0.7%",
      "changePercent": "+0.69",
      "status": "up"
    },
    "^DJI": {
      "price": "50,009.35",
      "changeText": "▲ 0.7%",
      "changePercent": "+0.65",
      "status": "up"
    },
    "^VIX": {
      "price": "17.44",
      "changeText": "안정",
      "changePercent": "-3.43",
      "status": "down"
    },
    "^RUT": {
      "price": "2,817.37",
      "changeText": "▲ 1.5%",
      "changePercent": "+1.52",
      "status": "up"
    },
    "CL=F": {
      "price": "99.08",
      "changeText": "▼ 8.1%",
      "changePercent": "-8.06",
      "status": "down"
    },
    "BZ=F": {
      "price": "105.53",
      "changeText": "▼ 5.2%",
      "changePercent": "-5.17",
      "status": "down"
    },
    "GC=F": {
      "price": "4,542.50",
      "changeText": "▲ 0.8%",
      "changePercent": "+0.80",
      "status": "up"
    },
    "SI=F": {
      "price": "75.92",
      "changeText": "▲ 1.5%",
      "changePercent": "+1.45",
      "status": "up"
    },
    "BTC-USD": {
      "price": "77,403.04",
      "changeText": "▲ 0.8%",
      "changePercent": "+0.85",
      "status": "up"
    },
    "ETH-USD": {
      "price": "2,124.83",
      "changeText": "▲ 0.7%",
      "changePercent": "+0.70",
      "status": "up"
    },
    "KRW=X": {
      "price": "1,496.5",
      "changeText": "▲ 0.3%",
      "changePercent": "+0.28",
      "status": "up"
    },
    "DX-Y.NYB": {
      "price": "99.13",
      "changeText": "▼ 0.2%",
      "changePercent": "-0.18",
      "status": "down"
    },
    "EURUSD=X": {
      "price": "1.16",
      "changeText": "▼ 0.2%",
      "changePercent": "-0.21",
      "status": "down"
    },
    "JPY=X": {
      "price": "158.82",
      "changeText": "▼ 0.0%",
      "changePercent": "-0.02",
      "status": "down"
    },
    "GBPUSD=X": {
      "price": "1.34",
      "changeText": "▲ 0.0%",
      "changePercent": "+0.04",
      "status": "up"
    },
    "^TNX": {
      "price": "4.57",
      "changeText": "▼ 9.5bp",
      "changePercent": "-2.04",
      "status": "down"
    },
    "^TYX": {
      "price": "5.12",
      "changeText": "▼ 6.5bp",
      "changePercent": "-1.25",
      "status": "down"
    },
    "^FVX": {
      "price": "4.23",
      "changeText": "▼ 10.5bp",
      "changePercent": "-2.42",
      "status": "down"
    },
    "^IRX": {
      "price": "3.56",
      "changeText": "▼ 1.8bp",
      "changePercent": "-0.50",
      "status": "down"
    },
    "AAPL": {
      "price": "302.25",
      "changeText": "▲ 1.5%",
      "changePercent": "+1.48",
      "status": "up"
    },
    "NVDA": {
      "price": "223.47",
      "changeText": "▲ 0.5%",
      "changePercent": "+0.52",
      "status": "up"
    },
    "META": {
      "price": "605.06",
      "changeText": "▼ 1.0%",
      "changePercent": "-1.01",
      "status": "down"
    },
    "MSFT": {
      "price": "421.06",
      "changeText": "▼ 0.6%",
      "changePercent": "-0.59",
      "status": "down"
    },
    "AMZN": {
      "price": "265.01",
      "changeText": "▲ 0.1%",
      "changePercent": "+0.06",
      "status": "up"
    },
    "GOOGL": {
      "price": "388.91",
      "changeText": "▼ 2.0%",
      "changePercent": "-2.02",
      "status": "down"
    },
    "TSLA": {
      "price": "417.26",
      "changeText": "▲ 1.8%",
      "changePercent": "+1.77",
      "status": "up"
    },
    "AMD": {
      "price": "447.58",
      "changeText": "▲ 6.3%",
      "changePercent": "+6.32",
      "status": "up"
    },
    "AVGO": {
      "price": "417.76",
      "changeText": "▼ 0.7%",
      "changePercent": "-0.70",
      "status": "down"
    },
    "PLTR": {
      "price": "137.15",
      "changeText": "▲ 1.5%",
      "changePercent": "+1.49",
      "status": "up"
    },
    "TSM": {
      "price": "401.62",
      "changeText": "▲ 1.4%",
      "changePercent": "+1.43",
      "status": "up"
    },
    "ARM": {
      "price": "256.73",
      "changeText": "▲ 19.3%",
      "changePercent": "+19.34",
      "status": "up"
    },
    "COIN": {
      "price": "191.29",
      "changeText": "▲ 1.0%",
      "changePercent": "+0.98",
      "status": "up"
    },
    "MSTR": {
      "price": "165.81",
      "changeText": "▼ 0.5%",
      "changePercent": "-0.49",
      "status": "down"
    },
    "SMCI": {
      "price": "33.46",
      "changeText": "▲ 8.5%",
      "changePercent": "+8.46",
      "status": "up"
    },
    "XLE": {
      "price": "59.80",
      "changeText": "▼ 1.3%",
      "changePercent": "-1.29",
      "status": "down"
    },
    "XLU": {
      "price": "44.51",
      "changeText": "▲ 1.3%",
      "changePercent": "+1.30",
      "status": "up"
    },
    "XLV": {
      "price": "147.13",
      "changeText": "▲ 1.0%",
      "changePercent": "+0.97",
      "status": "up"
    },
    "XLF": {
      "price": "51.66",
      "changeText": "▼ 0.2%",
      "changePercent": "-0.15",
      "status": "down"
    },
    "XLB": {
      "price": "49.72",
      "changeText": "▼ 1.0%",
      "changePercent": "-1.00",
      "status": "down"
    },
    "XLI": {
      "price": "170.73",
      "changeText": "▼ 0.0%",
      "changePercent": "-0.01",
      "status": "down"
    },
    "XLRE": {
      "price": "44.43",
      "changeText": "▲ 1.6%",
      "changePercent": "+1.55",
      "status": "up"
    },
    "XLP": {
      "price": "85.52",
      "changeText": "▼ 0.4%",
      "changePercent": "-0.44",
      "status": "down"
    },
    "XLY": {
      "price": "117.94",
      "changeText": "▲ 1.4%",
      "changePercent": "+1.39",
      "status": "up"
    },
    "VOX": {
      "price": "195.25",
      "changeText": "▼ 0.9%",
      "changePercent": "-0.95",
      "status": "down"
    },
    "XLK": {
      "price": "177.14",
      "changeText": "▲ 1.6%",
      "changePercent": "+1.59",
      "status": "up"
    }
  },
  "history": {
    "^GSPC": {
      "labels": [
        "5/7",
        "5/8",
        "5/11",
        "5/12",
        "5/13",
        "5/14",
        "5/15",
        "5/18",
        "5/19",
        "5/20"
      ],
      "values": [
        7337.11,
        7398.93,
        7412.84,
        7400.96,
        7444.25,
        7501.24,
        7408.5,
        7403.05,
        7353.61,
        7432.97
      ]
    },
    "^IXIC": {
      "labels": [
        "5/7",
        "5/8",
        "5/11",
        "5/12",
        "5/13",
        "5/14",
        "5/15",
        "5/18",
        "5/19",
        "5/20"
      ],
      "values": [
        25806.2,
        26247.08,
        26274.13,
        26088.2,
        26402.34,
        26635.22,
        26225.14,
        26090.73,
        25870.71,
        26270.36
      ]
    },
    "^DJI": {
      "labels": [
        "5/7",
        "5/8",
        "5/11",
        "5/12",
        "5/13",
        "5/14",
        "5/15",
        "5/18",
        "5/19",
        "5/20"
      ],
      "values": [
        49596.97,
        49609.16,
        49704.47,
        49760.56,
        49693.2,
        50063.46,
        49526.17,
        49686.12,
        49363.88,
        50009.35
      ]
    },
    "^VIX": {
      "labels": [
        "5/7",
        "5/8",
        "5/11",
        "5/12",
        "5/13",
        "5/14",
        "5/15",
        "5/18",
        "5/19",
        "5/20"
      ],
      "values": [
        17.08,
        17.19,
        18.38,
        17.99,
        17.87,
        17.26,
        18.43,
        17.82,
        18.06,
        17.44
      ]
    },
    "^RUT": {
      "labels": [
        "5/7",
        "5/8",
        "5/11",
        "5/12",
        "5/13",
        "5/14",
        "5/15",
        "5/18",
        "5/19",
        "5/20"
      ],
      "values": [
        2839.63,
        2861.21,
        2870.64,
        2842.83,
        2843.93,
        2863.09,
        2793.3,
        2775.1,
        2747.07,
        2817.36
      ]
    },
    "BTC-USD": {
      "labels": [
        "5/11",
        "5/12",
        "5/13",
        "5/14",
        "5/15",
        "5/16",
        "5/17",
        "5/18",
        "5/19",
        "5/20"
      ],
      "values": [
        81728.3,
        80477.49,
        79277.12,
        81051.25,
        79065.68,
        78131.44,
        77429.35,
        76954.17,
        76750.91,
        77403.04
      ]
    },
    "AAPL": {
      "labels": [
        "5/7",
        "5/8",
        "5/11",
        "5/12",
        "5/13",
        "5/14",
        "5/15",
        "5/18",
        "5/19",
        "5/20"
      ],
      "values": [
        287.44,
        293.32,
        292.68,
        294.8,
        298.87,
        298.21,
        300.23,
        297.84,
        298.97,
        302.25
      ]
    },
    "NVDA": {
      "labels": [
        "5/7",
        "5/8",
        "5/11",
        "5/12",
        "5/13",
        "5/14",
        "5/15",
        "5/18",
        "5/19",
        "5/20"
      ],
      "values": [
        211.5,
        215.2,
        219.44,
        220.78,
        225.83,
        235.74,
        225.32,
        222.32,
        220.61,
        223.47
      ]
    },
    "META": {
      "labels": [
        "5/7",
        "5/8",
        "5/11",
        "5/12",
        "5/13",
        "5/14",
        "5/15",
        "5/18",
        "5/19",
        "5/20"
      ],
      "values": [
        616.81,
        609.63,
        598.86,
        603,
        616.63,
        618.43,
        614.23,
        611.21,
        602.61,
        605.06
      ]
    },
    "MSFT": {
      "labels": [
        "5/7",
        "5/8",
        "5/11",
        "5/12",
        "5/13",
        "5/14",
        "5/15",
        "5/18",
        "5/19",
        "5/20"
      ],
      "values": [
        420.77,
        415.12,
        412.66,
        407.77,
        405.21,
        409.43,
        421.92,
        423.54,
        417.42,
        421.06
      ]
    },
    "AMZN": {
      "labels": [
        "5/7",
        "5/8",
        "5/11",
        "5/12",
        "5/13",
        "5/14",
        "5/15",
        "5/18",
        "5/19",
        "5/20"
      ],
      "values": [
        271.17,
        272.68,
        268.99,
        265.82,
        270.13,
        267.22,
        264.14,
        264.86,
        259.34,
        265.01
      ]
    },
    "GOOGL": {
      "labels": [
        "5/7",
        "5/8",
        "5/11",
        "5/12",
        "5/13",
        "5/14",
        "5/15",
        "5/18",
        "5/19",
        "5/20"
      ],
      "values": [
        397.99,
        400.8,
        388.64,
        387.35,
        402.62,
        401.07,
        396.78,
        396.94,
        387.66,
        388.91
      ]
    },
    "TSLA": {
      "labels": [
        "5/7",
        "5/8",
        "5/11",
        "5/12",
        "5/13",
        "5/14",
        "5/15",
        "5/18",
        "5/19",
        "5/20"
      ],
      "values": [
        411.79,
        428.35,
        445,
        433.45,
        445.27,
        443.3,
        422.24,
        409.99,
        404.11,
        417.26
      ]
    }
  },
  "sectors": {
    "Energy": {
      "price": "59.80",
      "changeText": "▼ 1.3%",
      "changePercent": "-1.29",
      "status": "down"
    },
    "Utilities": {
      "price": "44.51",
      "changeText": "▲ 1.3%",
      "changePercent": "+1.30",
      "status": "up"
    },
    "Health Care": {
      "price": "147.13",
      "changeText": "▲ 1.0%",
      "changePercent": "+0.97",
      "status": "up"
    },
    "Financials": {
      "price": "51.66",
      "changeText": "▼ 0.2%",
      "changePercent": "-0.15",
      "status": "down"
    },
    "Materials": {
      "price": "49.72",
      "changeText": "▼ 1.0%",
      "changePercent": "-1.00",
      "status": "down"
    },
    "Industrials": {
      "price": "170.73",
      "changeText": "▼ 0.0%",
      "changePercent": "-0.01",
      "status": "down"
    },
    "Real Estate": {
      "price": "44.43",
      "changeText": "▲ 1.6%",
      "changePercent": "+1.55",
      "status": "up"
    },
    "Consumer Staples": {
      "price": "85.52",
      "changeText": "▼ 0.4%",
      "changePercent": "-0.44",
      "status": "down"
    },
    "Consumer Discretionary": {
      "price": "117.94",
      "changeText": "▲ 1.4%",
      "changePercent": "+1.39",
      "status": "up"
    },
    "Communication": {
      "price": "195.25",
      "changeText": "▼ 0.9%",
      "changePercent": "-0.95",
      "status": "down"
    },
    "Technology": {
      "price": "177.14",
      "changeText": "▲ 1.6%",
      "changePercent": "+1.59",
      "status": "up"
    }
  },
  "yields": {
    "^IRX": {
      "price": "3.56",
      "changeText": "▼ 1.8bp",
      "changePercent": "-0.50",
      "status": "down"
    },
    "^FVX": {
      "price": "4.23",
      "changeText": "▼ 10.5bp",
      "changePercent": "-2.42",
      "status": "down"
    },
    "^TNX": {
      "price": "4.57",
      "changeText": "▼ 9.5bp",
      "changePercent": "-2.04",
      "status": "down"
    },
    "^TYX": {
      "price": "5.12",
      "changeText": "▼ 6.5bp",
      "changePercent": "-1.25",
      "status": "down"
    }
  },
  "macros": {
    "cpi": {
      "value": 3.8,
      "label": "4월 기준",
      "status": "dn"
    },
    "unemployment": {
      "value": 4.3,
      "label": "4월 기준",
      "status": "up"
    },
    "fedRate": {
      "value": 3.64,
      "label": "현재 기준금리",
      "status": "neu"
    },
    "pce": {
      "value": 3.2,
      "label": "3월 기준",
      "status": "warn"
    }
  },
  "commentary": {
    "brief": "미국 주식 시장은 채권 시장의 압력이 완화되고 유가 상승세가 꺾이면서 반등했습니다. 연준의 4월 회의록에 따르면 일부 정책위원들은 금리 인상에 대한 기반을 다져야 한다고 주장하면서 인플레이션 우려가 커지고 있으며, 우크라이나 전쟁으로 인해 기업들은 공급망 문제와 사이버 공격의 위험에 직면해 있습니다.",
    "topics": [
      {
        "title": "연준의 인플레이션 우려와 금리 인상 가능성",
        "description": "4월 연방공개시장위원회(FOMC) 회의록에 따르면 일부 정책위원들은 이란 전쟁으로 인한 인플레이션 압력에 대한 우려를 표명하며 금리 인상 가능성을 시사했습니다. 4명의 정책위원이 금리 동결에 반대했는데, 이는 1992년 이후 가장 많은 수치입니다."
      },
      {
        "title": "유가 하락과 채권 시장 안정",
        "description": "유가가 하락하고 채권 수익률이 안정되면서 주식 시장에 긍정적인 영향을 미쳤습니다. 10년 만기 미국 국채 수익률은 4.60% 아래로 하락했으며, 브렌트유 가격은 5.6% 하락했습니다."
      },
      {
        "title": "기업 실적 호조",
        "description": "TJX와 Red Robin Gourmet Burgers, Cava Group 등 다수 기업이 예상치를 상회하는 실적을 발표하면서 소비 지출이 지속될 수 있다는 기대감을 높였습니다. 이는 주식 시장의 상승세에 기여했습니다."
      },
      {
        "title": "지정학적 리스크와 공급망 문제",
        "description": "우크라이나 전쟁과 중동 지역의 긴장 고조로 인해 기업들은 공급망 차질, 시장 접근성 상실, 사이버 공격 위험 증가 등 심각한 문제에 직면해 있습니다. Allianz Commercial 보고서에 따르면 전쟁은 기업들이 가장 우려하는 정치적 폭력 위험으로 부상했습니다."
      }
    ],
    "events": [
      {
        "date": "3. 4. (화)",
        "description": "구체적인 이벤트 이름이 없습니다."
      }
    ]
  }
}