{
  "lastUpdated": "2026-05-12T22:38:04.996Z",
  "indices": {
    "^GSPC": {
      "price": "7,400.96",
      "changeText": "▲ 0.0%",
      "changePercent": "+0.03",
      "status": "up"
    },
    "^IXIC": {
      "price": "26,088.20",
      "changeText": "▼ 0.6%",
      "changePercent": "-0.61",
      "status": "down"
    },
    "^DJI": {
      "price": "49,760.56",
      "changeText": "▲ 0.3%",
      "changePercent": "+0.31",
      "status": "up"
    },
    "^VIX": {
      "price": "17.99",
      "changeText": "안정",
      "changePercent": "-2.12",
      "status": "down"
    },
    "^RUT": {
      "price": "2,842.83",
      "changeText": "▼ 0.6%",
      "changePercent": "-0.64",
      "status": "down"
    },
    "CL=F": {
      "price": "101.82",
      "changeText": "▲ 3.8%",
      "changePercent": "+3.82",
      "status": "up"
    },
    "BZ=F": {
      "price": "107.22",
      "changeText": "▲ 2.9%",
      "changePercent": "+2.89",
      "status": "up"
    },
    "GC=F": {
      "price": "4,722.80",
      "changeText": "▲ 0.1%",
      "changePercent": "+0.09",
      "status": "up"
    },
    "SI=F": {
      "price": "87.54",
      "changeText": "▲ 2.4%",
      "changePercent": "+2.40",
      "status": "up"
    },
    "BTC-USD": {
      "price": "80,624.21",
      "changeText": "▼ 1.4%",
      "changePercent": "-1.35",
      "status": "down"
    },
    "ETH-USD": {
      "price": "2,284.66",
      "changeText": "▼ 2.3%",
      "changePercent": "-2.34",
      "status": "down"
    },
    "KRW=X": {
      "price": "1,492.2",
      "changeText": "▲ 2.2%",
      "changePercent": "+2.17",
      "status": "up"
    },
    "DX-Y.NYB": {
      "price": "98.29",
      "changeText": "▲ 0.4%",
      "changePercent": "+0.36",
      "status": "up"
    },
    "EURUSD=X": {
      "price": "1.17",
      "changeText": "▼ 0.2%",
      "changePercent": "-0.22",
      "status": "down"
    },
    "JPY=X": {
      "price": "157.62",
      "changeText": "▲ 0.5%",
      "changePercent": "+0.48",
      "status": "up"
    },
    "GBPUSD=X": {
      "price": "1.35",
      "changeText": "▼ 0.4%",
      "changePercent": "-0.40",
      "status": "down"
    },
    "^TNX": {
      "price": "4.46",
      "changeText": "▲ 5.3bp",
      "changePercent": "+1.20",
      "status": "warn"
    },
    "^TYX": {
      "price": "5.03",
      "changeText": "▲ 4.5bp",
      "changePercent": "+0.90",
      "status": "warn"
    },
    "^FVX": {
      "price": "4.12",
      "changeText": "▲ 5.6bp",
      "changePercent": "+1.38",
      "status": "warn"
    },
    "^IRX": {
      "price": "3.60",
      "changeText": "▲ 0.3bp",
      "changePercent": "+0.08",
      "status": "warn"
    },
    "AAPL": {
      "price": "294.80",
      "changeText": "▲ 0.5%",
      "changePercent": "+0.50",
      "status": "up"
    },
    "NVDA": {
      "price": "220.78",
      "changeText": "▲ 2.6%",
      "changePercent": "+2.59",
      "status": "up"
    },
    "META": {
      "price": "603.00",
      "changeText": "▼ 1.1%",
      "changePercent": "-1.09",
      "status": "down"
    },
    "MSFT": {
      "price": "407.77",
      "changeText": "▼ 1.8%",
      "changePercent": "-1.77",
      "status": "down"
    },
    "AMZN": {
      "price": "265.82",
      "changeText": "▼ 2.5%",
      "changePercent": "-2.52",
      "status": "down"
    },
    "GOOGL": {
      "price": "387.35",
      "changeText": "▼ 3.4%",
      "changePercent": "-3.36",
      "status": "down"
    },
    "TSLA": {
      "price": "433.45",
      "changeText": "▲ 1.2%",
      "changePercent": "+1.19",
      "status": "up"
    },
    "AMD": {
      "price": "448.29",
      "changeText": "▼ 1.5%",
      "changePercent": "-1.52",
      "status": "down"
    },
    "AVGO": {
      "price": "419.30",
      "changeText": "▼ 2.5%",
      "changePercent": "-2.49",
      "status": "down"
    },
    "PLTR": {
      "price": "136.00",
      "changeText": "▼ 1.3%",
      "changePercent": "-1.31",
      "status": "down"
    },
    "TSM": {
      "price": "397.28",
      "changeText": "▼ 3.5%",
      "changePercent": "-3.50",
      "status": "down"
    },
    "ARM": {
      "price": "207.92",
      "changeText": "▼ 2.5%",
      "changePercent": "-2.51",
      "status": "down"
    },
    "COIN": {
      "price": "207.64",
      "changeText": "▲ 3.2%",
      "changePercent": "+3.22",
      "status": "up"
    },
    "MSTR": {
      "price": "184.42",
      "changeText": "▼ 1.7%",
      "changePercent": "-1.69",
      "status": "down"
    },
    "SMCI": {
      "price": "32.79",
      "changeText": "▼ 7.3%",
      "changePercent": "-7.29",
      "status": "down"
    },
    "XLE": {
      "price": "57.57",
      "changeText": "▲ 3.4%",
      "changePercent": "+3.36",
      "status": "up"
    },
    "XLU": {
      "price": "45.19",
      "changeText": "▲ 1.1%",
      "changePercent": "+1.05",
      "status": "up"
    },
    "XLV": {
      "price": "145.85",
      "changeText": "▲ 1.6%",
      "changePercent": "+1.64",
      "status": "up"
    },
    "XLF": {
      "price": "51.58",
      "changeText": "▲ 0.7%",
      "changePercent": "+0.66",
      "status": "up"
    },
    "XLB": {
      "price": "52.14",
      "changeText": "▲ 1.1%",
      "changePercent": "+1.07",
      "status": "up"
    },
    "XLI": {
      "price": "174.35",
      "changeText": "▲ 0.7%",
      "changePercent": "+0.66",
      "status": "up"
    },
    "XLRE": {
      "price": "44.58",
      "changeText": "▲ 0.4%",
      "changePercent": "+0.38",
      "status": "up"
    },
    "XLP": {
      "price": "84.44",
      "changeText": "▲ 0.3%",
      "changePercent": "+0.31",
      "status": "up"
    },
    "XLY": {
      "price": "118.29",
      "changeText": "▼ 1.6%",
      "changePercent": "-1.59",
      "status": "down"
    },
    "VOX": {
      "price": "194.56",
      "changeText": "▼ 1.6%",
      "changePercent": "-1.59",
      "status": "down"
    },
    "XLK": {
      "price": "175.20",
      "changeText": "▼ 0.2%",
      "changePercent": "-0.18",
      "status": "down"
    }
  },
  "history": {
    "^GSPC": {
      "labels": [
        "4/29",
        "4/30",
        "5/1",
        "5/4",
        "5/5",
        "5/6",
        "5/7",
        "5/8",
        "5/11",
        "5/12"
      ],
      "values": [
        7135.95,
        7209.01,
        7230.12,
        7200.75,
        7259.22,
        7365.12,
        7337.11,
        7398.93,
        7412.84,
        7400.96
      ]
    },
    "^IXIC": {
      "labels": [
        "4/29",
        "4/30",
        "5/1",
        "5/4",
        "5/5",
        "5/6",
        "5/7",
        "5/8",
        "5/11",
        "5/12"
      ],
      "values": [
        24673.24,
        24892.31,
        25114.44,
        25067.8,
        25326.13,
        25838.94,
        25806.2,
        26247.08,
        26274.13,
        26088.2
      ]
    },
    "^DJI": {
      "labels": [
        "4/29",
        "4/30",
        "5/1",
        "5/4",
        "5/5",
        "5/6",
        "5/7",
        "5/8",
        "5/11",
        "5/12"
      ],
      "values": [
        48861.81,
        49652.14,
        49499.27,
        48941.9,
        49298.25,
        49910.59,
        49596.97,
        49609.16,
        49704.47,
        49760.56
      ]
    },
    "^VIX": {
      "labels": [
        "4/29",
        "4/30",
        "5/1",
        "5/4",
        "5/5",
        "5/6",
        "5/7",
        "5/8",
        "5/11",
        "5/12"
      ],
      "values": [
        18.81,
        16.89,
        16.99,
        18.29,
        17.38,
        17.39,
        17.08,
        17.19,
        18.38,
        17.99
      ]
    },
    "^RUT": {
      "labels": [
        "4/29",
        "4/30",
        "5/1",
        "5/4",
        "5/5",
        "5/6",
        "5/7",
        "5/8",
        "5/11",
        "5/12"
      ],
      "values": [
        2739.47,
        2799.91,
        2812.82,
        2796,
        2845,
        2886.77,
        2839.63,
        2861.21,
        2870.64,
        2842.83
      ]
    },
    "BTC-USD": {
      "labels": [
        "5/3",
        "5/4",
        "5/5",
        "5/6",
        "5/7",
        "5/8",
        "5/9",
        "5/10",
        "5/11",
        "5/12"
      ],
      "values": [
        78538.23,
        79827.91,
        80927.05,
        81427.53,
        80009.99,
        80186.77,
        80664.37,
        82138.93,
        81728.3,
        80624.21
      ]
    },
    "AAPL": {
      "labels": [
        "4/29",
        "4/30",
        "5/1",
        "5/4",
        "5/5",
        "5/6",
        "5/7",
        "5/8",
        "5/11",
        "5/12"
      ],
      "values": [
        270.17,
        271.35,
        280.14,
        276.83,
        284.18,
        287.51,
        287.44,
        293.32,
        292.68,
        294.8
      ]
    },
    "NVDA": {
      "labels": [
        "4/29",
        "4/30",
        "5/1",
        "5/4",
        "5/5",
        "5/6",
        "5/7",
        "5/8",
        "5/11",
        "5/12"
      ],
      "values": [
        209.25,
        199.57,
        198.45,
        198.48,
        196.5,
        207.83,
        211.5,
        215.2,
        219.44,
        220.78
      ]
    },
    "META": {
      "labels": [
        "4/29",
        "4/30",
        "5/1",
        "5/4",
        "5/5",
        "5/6",
        "5/7",
        "5/8",
        "5/11",
        "5/12"
      ],
      "values": [
        669.12,
        611.91,
        608.75,
        610.41,
        604.96,
        612.88,
        616.81,
        609.63,
        598.86,
        603
      ]
    },
    "MSFT": {
      "labels": [
        "4/29",
        "4/30",
        "5/1",
        "5/4",
        "5/5",
        "5/6",
        "5/7",
        "5/8",
        "5/11",
        "5/12"
      ],
      "values": [
        424.46,
        407.78,
        414.44,
        413.62,
        411.38,
        413.96,
        420.77,
        415.12,
        412.66,
        407.77
      ]
    },
    "AMZN": {
      "labels": [
        "4/29",
        "4/30",
        "5/1",
        "5/4",
        "5/5",
        "5/6",
        "5/7",
        "5/8",
        "5/11",
        "5/12"
      ],
      "values": [
        263.04,
        265.06,
        268.26,
        272.05,
        273.55,
        274.99,
        271.17,
        272.68,
        268.99,
        265.82
      ]
    },
    "GOOGL": {
      "labels": [
        "4/29",
        "4/30",
        "5/1",
        "5/4",
        "5/5",
        "5/6",
        "5/7",
        "5/8",
        "5/11",
        "5/12"
      ],
      "values": [
        349.94,
        384.8,
        385.69,
        383.25,
        388.43,
        398.04,
        397.99,
        400.8,
        388.64,
        387.35
      ]
    },
    "TSLA": {
      "labels": [
        "4/29",
        "4/30",
        "5/1",
        "5/4",
        "5/5",
        "5/6",
        "5/7",
        "5/8",
        "5/11",
        "5/12"
      ],
      "values": [
        372.8,
        381.63,
        390.82,
        392.51,
        389.37,
        398.73,
        411.79,
        428.35,
        445,
        433.45
      ]
    }
  },
  "sectors": {
    "Energy": {
      "price": "57.57",
      "changeText": "▲ 3.4%",
      "changePercent": "+3.36",
      "status": "up"
    },
    "Utilities": {
      "price": "45.19",
      "changeText": "▲ 1.1%",
      "changePercent": "+1.05",
      "status": "up"
    },
    "Health Care": {
      "price": "145.85",
      "changeText": "▲ 1.6%",
      "changePercent": "+1.64",
      "status": "up"
    },
    "Financials": {
      "price": "51.58",
      "changeText": "▲ 0.7%",
      "changePercent": "+0.66",
      "status": "up"
    },
    "Materials": {
      "price": "52.14",
      "changeText": "▲ 1.1%",
      "changePercent": "+1.07",
      "status": "up"
    },
    "Industrials": {
      "price": "174.35",
      "changeText": "▲ 0.7%",
      "changePercent": "+0.66",
      "status": "up"
    },
    "Real Estate": {
      "price": "44.58",
      "changeText": "▲ 0.4%",
      "changePercent": "+0.38",
      "status": "up"
    },
    "Consumer Staples": {
      "price": "84.44",
      "changeText": "▲ 0.3%",
      "changePercent": "+0.31",
      "status": "up"
    },
    "Consumer Discretionary": {
      "price": "118.29",
      "changeText": "▼ 1.6%",
      "changePercent": "-1.59",
      "status": "down"
    },
    "Communication": {
      "price": "194.56",
      "changeText": "▼ 1.6%",
      "changePercent": "-1.59",
      "status": "down"
    },
    "Technology": {
      "price": "175.20",
      "changeText": "▼ 0.2%",
      "changePercent": "-0.18",
      "status": "down"
    }
  },
  "yields": {
    "^IRX": {
      "price": "3.60",
      "changeText": "▲ 0.3bp",
      "changePercent": "+0.08",
      "status": "warn"
    },
    "^FVX": {
      "price": "4.12",
      "changeText": "▲ 5.6bp",
      "changePercent": "+1.38",
      "status": "warn"
    },
    "^TNX": {
      "price": "4.46",
      "changeText": "▲ 5.3bp",
      "changePercent": "+1.20",
      "status": "warn"
    },
    "^TYX": {
      "price": "5.03",
      "changeText": "▲ 4.5bp",
      "changePercent": "+0.90",
      "status": "warn"
    }
  },
  "macros": {
    "cpi": {
      "value": 3.8,
      "label": "4월 기준",
      "status": "dn"
    },
    "unemployment": {
      "value": 4.3,
      "label": "4월 기준",
      "status": "up"
    },
    "fedRate": {
      "value": 3.64,
      "label": "현재 기준금리",
      "status": "neu"
    },
    "pce": {
      "value": 3.2,
      "label": "3월 기준",
      "status": "warn"
    }
  },
  "commentary": {
    "brief": "미국 시장은 5월 12일 혼조세를 보였으며, 다우존스는 소폭 상승, S&P 500은 거의 변동이 없었지만 나스닥은 하락했습니다. 4월 소비자물가지수(CPI)가 예상치를 소폭 상회하면서 인플레이션 우려가 지속되었고, 미-이란 간 긴장 고조가 시장에 영향을 미쳤습니다.",
    "topics": [
      {
        "title": "지속적인 인플레이션 압력",
        "description": "미국 노동부는 4월 소비자물가지수(CPI)가 전년 동월 대비 3.8% 상승했다고 발표했는데, 이는 시장 예상치인 3.7%를 소폭 상회하는 수치입니다. 에너지 및 식품 가격 상승이 주요 원인으로 지목되었으며, 이는 연준의 금리 인하에 대한 신중한 접근을 시사합니다."
      },
      {
        "title": "미-이란 긴장 고조",
        "description": "미국과 이란 간의 갈등이 고조되면서 국제 유가가 상승했으며, 이는 시장에 부정적인 영향을 미쳤습니다. 도널드 트럼프 대통령은 이란이 제시한 종전안에 대해 '멍청한 제안'이라고 평가하여, 단기적인 긴장 완화 가능성을 낮췄습니다."
      },
      {
        "title": "주요 기술주의 혼조세",
        "description": "엔비디아와 애플은 각각 1.21%, 0.29% 상승했지만, 마이크로소프트는 1.28%, 아마존닷컴은 1.33%, 알파벳A는 0.48% 하락하는 등 대부분의 기술주가 약세를 보였습니다. 이는 기술주 전반에 걸친 투자 심리가 엇갈리고 있음을 나타냅니다."
      },
      {
        "title": "펄어비스 1분기 최대 실적",
        "description": "펄어비스는 붉은사막의 흥행에 힘입어 1분기 매출 3285억 원, 영업이익 2121억 원을 달성하며 흑자 전환에 성공했습니다. 붉은사막은 출시 26일 만에 500만 장 판매를 돌파하며 실적을 견인했고, 콘솔 매출 비중도 전 분기 대비 31% 급증했습니다."
      }
    ],
    "events": [
      {
        "date": "5. 14~15",
        "description": "트럼프-시진핑 베이징 회담"
      },
      {
        "date": "5. 20",
        "description": "엔비디아 1분기 어닝 발표"
      }
    ]
  }
}